<?xml version='1.0' encoding='ISO-8859-1'?>
<!DOCTYPE shader SYSTEM "DEOpenGLShader.dtd">
<shader>
	<name>Debug Display Texture</name>
	
	<version>150</version>
	
	<texture name="texTexture" target="0"/>
	
	<parameter name="pPosTransform"/> <!-- 0 -->
	<parameter name="pTCTransform"/> <!-- 1 -->
	<parameter name="pColor"/> <!-- 2 -->
	<parameter name="pGamma"/> <!-- 3 -->
	<parameter name="pLevel"/> <!-- 4 -->
	<parameter name="pLayer"/> <!-- 5 -->
	
	<attribute name="inPosition" target="0"/>
	
	<output name="outColor" target="0"/>
	
	<sourceCode unit="vertex">v130/vertex/generic/screenspace.glsl</sourceCode>
	<sourceCode unit="fragment">v130/fragment/generic/output_texture.glsl</sourceCode>
</shader>
