<?xml version='1.0' encoding='ISO-8859-1'?>
<shader>
	<name>DefRen Depth Downsample</name>
	
	<texture name='texDepth' target='0'/>
	
	<parameter name='pTCClamp'/> <!-- 0 -->
	<parameter name='pMipMapLevel'/> <!-- 1 -->
	
	<attribute name='inPosition' target='0'/>
	<attribute name='inLayer' target='1'/>
	
	<output name='outDepth' target='0'/>
	
	<sourceCode unit='vertex'>v130/vertex/generic/fullscreenquad.glsl</sourceCode>
	<sourceCode unit='fragment'>v130/fragment/defren/depth_downsample.glsl</sourceCode>
</shader>
